Workbook

Sheet Enero 2026
E2: Fondo Inversión | F2: Fondo Rico | G2: Fondo Estudio/CAE | H2: Fondo Emergencia | I2: Fondo Dar | J2: Fondo Libre | K2: Fondo Camilo | L2: Crédito | M2: Fondo Papá | N2: Empresa | O2: Fondo Extra
E3: 0 | F3: 0 | G3: 1178016 | H3: 0 | I3: $0 | J3: 182362 | K3: 78220 | L3: 0 | M3: 0 | N3: 1055061 | O3: 1000000
B4: Sueldo Líquido | C4: Total | G4: -22685 | J4: -10000 | K4: -3000 | L4: -122714 | M4: 150000
B5: 0 | C5: =B5 -> 0 | J5: -3500 | K5: -11863 | L5: 122714 | M5: -150000
J6: 416479 | K6: -32528 | M6: 300000
B7: Cargos del Mes | C7: Gastos del Fondo Libre | J7: -10000 | K7: -2700 | M7: -300000
B8: =SUMIF(E3:O33,"<0")*-1 -> 1461256 | C8: =SUMIF(J3:J33,"<0")*-1 -> 603039 | J8: -57150 | K8: -27252
J9: =1410 -> 1410 | K9: -2730
J10: -10000 | K10: -5000
J11: =2850 -> 2850 | K11: -2439
J12: -9027 | K12: =300000 -> 300000
J13: -22523 | K13: -135306
J14: =2820 -> 2820 | K14: -40000
J15: -23140
J16: -10000
J17: -15990
J18: -17400
J19: -10000
J20: 110000
J21: 160459
J22: -30463
J23: =-22886*2 -> -45772
J24: =-22886*2 -> -45772
J25: -24713
J26: -33000
J27: -36037
J28: -67700
J29: -29933
J30: -49993
J31: -19993
J32: -11000
J33: -9933
D36: Total c/u | E36: =SUM(E3:E33) -> 0 | F36: =SUM(F3:F33) -> 0 | G36: =SUM(G3:G33) -> 1155331 | H36: =SUM(H3:H33) -> 0 | I36: =SUM(I3:I33) -> 0 | J36: =SUM(J3:J33) -> 273341 | K36: =SUM(K3:K33) -> 115402 | L36: =SUM(L3:L33) -> 0 | ... O36: =SUM(O3:O33) -> 1000000 | P36: =SUM(E36:O36) -> 3599135

Sheet Febrero 2026
E2: Fondo Inversión | F2: Fondo Rico | G2: Fondo Estudio/CAE | H2: Fondo Emergencia | I2: Fondo Dar | J2: Fondo Libre | K2: Fondo Camilo | L2: Crédito | M2: Fondo Papá | N2: Empresa | O2: Fondo Extra
E3: ='Enero 2026'!E36 -> 0 | F3: ='Enero 2026'!F36 -> 0 | G3: ='Enero 2026'!G36 -> 1155331 | H3: ='Enero 2026'!H36 -> 0 | I3: ='Enero 2026'!I36 -> 0 | J3: ='Enero 2026'!J36 -> 273341 | K3: ='Enero 2026'!K36 -> 115402 | L3: ='Enero 2026'!L36 -> 0 | ... O3: ='Enero 2026'!O36 -> 1000000
B4: Sueldo Líquido | C4: Total | G4: -22648 | J4: -10000 | K4: -2000 | L4: 122714 | M4: =150000 -> 150000 | N4: -14067
B5: 0 | C5: =B5 -> 0 | J5: -14150 | K5: -12090 | M5: -2780
J6: -10000 | K6: -4720 | M6: -2987
B7: Cargos del Mes | C7: Gastos del Fondo Libre | J7: 287908 | K7: -3408 | M7: -3132
B8: =SUMIF(E3:O31,"<0")*-1 -> 1193035 | C8: =SUMIF(J3:J31,"<0")*-1 -> 331555 | J8: -9027 | K8: -109269 | M8: -8525
J9: -24268 | K9: -2400 | M9: -2740
J10: =2496 -> 2496 | K10: -4350 | M10: 300000
J11: -3300 | K11: 300000 | M11: -2330
J12: -10000 | K12: 100000 | M12: -100000
J13: -5000 | K13: -195532 | M13: -300000
J14: -30600 | K14: -40000
J15: -10000 | K15: -28502
J16: -1100
J17: 50000
J18: 78642
J19: -5100
J20: -10000
J21: -30010
J22: -24713
J23: -29934
J24: -49994
J25: -19993
J26: -11000
J27: -13430
J28: -9936
D34: Total c/u | E34: =SUM(E3:E31) -> 0 | F34: =SUM(F3:F31) -> 0 | G34: =SUM(G3:G31) -> 1132683 | H34: =SUM(H3:H31) -> 0 | I34: =SUM(I3:I31) -> 0 | J34: =SUM(J3:J31) -> 360832 | K34: =SUM(K3:K31) -> 113131 | L34: =SUM(L3:L31) -> 122714 | ... O34: =SUM(O3:O31) -> 1000000 | P34: =SUM(E34:O34) -> 3797860

Sheet Marzo 2026
E2: Fondo Inversión | F2: Fondo Rico | G2: Fondo Estudio/CAE | H2: Fondo Emergencia | I2: Fondo Dar | J2: Fondo Libre | K2: Fondo Camilo | L2: Crédito | M2: Fondo Papá | N2: Empresa | O2: Fondo Extra
E3: ='Febrero 2026'!E34 -> 0 | F3: ='Febrero 2026'!F34 -> 0 | G3: ='Febrero 2026'!G34 -> 1132683 | H3: ='Febrero 2026'!H34 -> 0 | I3: ='Febrero 2026'!I34 -> 0 | J3: ='Febrero 2026'!J34 -> 360832 | K3: ='Febrero 2026'!K34 -> 113131 | L3: ='Febrero 2026'!L34 -> 122714 | ... O3: ='Febrero 2026'!O34 -> 1000000
B4: Sueldo Líquido | C4: Total | G4: -22733 | J4: -12398 | K4: -1330 | L4: -122714 | M4: -27506 | O4: 100230
B5: 0 | C5: =B5 -> 0 | J5: -4290 | K5: -2000 | M5: 150000 | O5: 110000
J6: -758 | K6: -51569 | M6: -150000 | O6: =30000 -> 30000
B7: Cargos del Mes | C7: Gastos del Fondo Libre | J7: -9027 | K7: -1700 | M7: 300000 | O7: 585386
B8: =SUMIF(E3:O36,"<0")*-1 -> 1114648 | C8: =SUMIF(J3:J36,"<0")*-1 -> 481265 | J8: -24268 | K8: =M4*-1 -> 27506
J9: -21140 | K9: -2100
J10: -10000 | K10: -3199
J11: =3079 -> 3079 | K11: -2492
J12: -10000 | K12: -11650
J13: -1400 | K13: -2050
J14: -35840 | K14: -2150
J15: -5000 | K15: -7182
J16: -27330 | K16: -4020
J17: 3079 | K17: -15305
J18: -10000 | K18: -11500
J19: -10590 | K19: -3294
J20: -10000 | K20: 300000
J21: -30956 | K21: -188889
J22: -9600
J23: =100000 -> 100000
J24: 173332
J25: -45772
J26: -45772
J27: -24713
J28: -67434
J29: -19994
J30: -11000
J31: -13430
J32: -9997
J33: -596
J34: -9960
J35: 324719
D39: Total c/u | E39: =SUM(E3:E36) -> 0 | F39: =SUM(F3:F36) -> 0 | G39: =SUM(G3:G36) -> 1109950 | H39: =SUM(H3:H36) -> 0 | I39: =SUM(I3:I36) -> 0 | J39: =SUM(J3:J36) -> 483776 | K39: =SUM(K3:K36) -> 130207 | L39: =SUM(L3:L36) -> 0 | ... O39: =SUM(O3:O36) -> 1825616 | P39: =SUM(E39:O39) -> 4890543

Sheet Abril 2026
E2: Fondo Inversión | F2: Fondo Rico | G2: Fondo Estudio/CAE | H2: Fondo Emergencia | I2: Fondo Dar | J2: Fondo Libre | K2: Fondo Camilo | L2: Fondo Papá | M2: Empresa | N2: Fondo Moto
E3: ='Marzo 2026'!E39 -> 0 | F3: ='Marzo 2026'!F39 -> 0 | G3: ='Marzo 2026'!G39 -> 1109950 | H3: ='Marzo 2026'!H39 -> 0 | I3: ='Marzo 2026'!I39 -> 0 | J3: ='Marzo 2026'!J39 -> 483776 | K3: ='Marzo 2026'!K39 -> 130207 | L3: ='Marzo 2026'!M39 -> 300000 | M3: ='Marzo 2026'!N39 -> 1040994 | N3: ='Marzo 2026'!O39 -> 1825616
B4: Sueldo Líquido | C4: Total | G4: -22733 | J4: -10000 | K4: -40000 | L4: -300000 | M4: -40000
B5: 0 | C5: =B5 -> 0 | J5: -2000 | K5: -3657 | L5: =150000 -> 150000 | M5: -63114
J6: -24268 | K6: -3000 | L6: -150000 | M6: -52008
B7: Cargos del Mes | C7: Gastos del Fondo Libre | J7: -23150 | K7: -25000 | L7: =300000 -> 300000 | M7: -1600
B8: =SUMIF(E3:N31,"<0")*-1 -> 1431294 | C8: =SUMIF(J3:J31,"<0")*-1 -> 126425 | J8: -10000 | K8: -3000 | L8: -300000
J9: -15000 | K9: -10040
J10: -10000 | K10: -2470
J11: -9027 | K11: -2000
J12: -10000 | K12: -2239
J13: -10280 | K13: -3596
J14: -2700 | K14: -3574
K15: -3070
K16: -10130
K17: -8000
K18: -16630
K19: -13890
K20: =350000 -> 350000
K21: -165118
K22: -60000
D34: Total c/u | E34: =SUM(E3:E31) -> 0 | F34: =SUM(F3:F31) -> 0 | G34: =SUM(G3:G31) -> 1087217 | H34: =SUM(H3:H31) -> 0 | I34: =SUM(I3:I31) -> 0 | J34: =SUM(J3:J31) -> 357351 | K34: =SUM(K3:K31) -> 104793 | L34: =SUM(L3:L31) -> 0 | ... N34: =SUM(N3:N31) -> 1825616 | O34: =SUM(E34:N34) -> 4259249

Sheet Mayo 2026
E2: Fondo Inversión | F2: Fondo Rico | G2: Fondo Estudio/CAE | H2: Fondo Emergencia | I2: Fondo Dar | J2: Fondo Libre | K2: Fondo Javier | L2: Fondo Camilo | M2: Fondo Papá | N2: Empresa | O2: Fondo Moto
E3: ='Abril 2026'!E34 -> 0 | F3: ='Abril 2026'!F34 -> 0 | G3: ='Abril 2026'!G34 -> 1087217 | H3: ='Abril 2026'!H34 -> 0 | I3: ='Abril 2026'!I34 -> 0 | J3: ='Abril 2026'!J34 -> 357351 | K3: 0 | L3: ='Abril 2026'!K34 -> 104793 | M3: ='Abril 2026'!L34 -> 0 | N3: ='Abril 2026'!M34 -> 884272 | O3: ='Abril 2026'!N34 -> 1825616
B4: Sueldo Líquido | C4: Total | G4: -22923 | J4: -91748 | K4: -24608 | L4: -2040 | M4: =150000 -> 150000 | O4: =219643 -> 219643
B5: 0 | C5: =B5 -> 0 | J5: -9027 | K5: -15090 | L5: -25938 | M5: -150000
J6: -10100 | L6: -30016 | M6: -40000
J7: 142381 | L7: -2794 | M7: =300000 -> 300000
B8: Cargos del Mes | C8: Gastos del Fondo Libre | J8: 124953 | L8: -33242
B9: =SUMIF(E3:O34,"<0")*-1 -> 900207 | C9: =SUMIF(J3:J34,"<0")*-1 -> 528543 | J9: -22886 | L9: -2957
J10: -22886 | L10: -3609
J11: -24713 | L11: -4197
J12: -25733 | L12: -10480
J13: -73800 | L13: 300000
J14: -13430 | L14: -3770
J15: -78149
J16: -9997
J17: -16663
J18: -248
J19: -10003
J20: -10000
J21: -10000
J22: -13394
J23: =2441 -> 2441
J24: -10000
J25: -10000
J26: -5700
J27: -10000
J28: -20000
J29: -30066
J30: 131332
D37: Total c/u | E37: =SUM(E3:E34) -> 0 | F37: =SUM(F3:F34) -> 0 | G37: =SUM(G3:G34) -> 1064294 | H37: =SUM(H3:H34) -> 0 | I37: =SUM(I3:I34) -> 0 | J37: =SUM(J3:J34) -> 229915 | K37: =SUM(K3:K34) -> -39698 | L37: =SUM(L3:L34) -> 285750 | ... O37: =SUM(O3:O34) -> 2045259 | P37: =SUM(E37:O37) -> 4729792

Sheet Junio 2026
E2: Fondo Inversión | F2: Fondo Rico | G2: Fondo Estudio/CAE | H2: Fondo Emergencia | I2: Fondo Dar | J2: Fondo Libre | K2: Fondo Javier | L2: Fondo Camilo | M2: Fondo Papá | N2: Empresa | O2: Fondo Moto
E3: ='Mayo 2026'!E37 -> 0 | F3: ='Mayo 2026'!F37 -> 0 | G3: ='Mayo 2026'!G37 -> 1064294 | H3: ='Mayo 2026'!H37 -> 0 | I3: ='Mayo 2026'!I37 -> 0 | J3: ='Mayo 2026'!J37 -> 229915 | K3: ='Mayo 2026'!K37 -> -39698 | L3: ='Mayo 2026'!L37 -> 285750 | ... O3: ='Mayo 2026'!O37 -> 2045259
B4: Sueldo Líquido | C4: Total | G4: -23182 | J4: =145834+'Mayo 2026'!K4+'Mayo 2026'!K5 -> 106136 | K4: 24608 | L4: -3900 | M4: -260000 | O4: -148652
B5: 0 | C5: =B5 -> 0 | J5: -10000 | K5: 15090 | L5: -60000 | M5: 150000 | O5: 62000
J6: -22886 | K6: -8900 | L6: -195899 | M6: -150000 | O6: -80800
J7: -22886 | K7: -29070 | L7: -1900 | O7: -62000
B8: Cargos del Mes | C8: Gastos del Fondo Libre | J8: -24713 | K8: -24608 | L8: -2920 | O8: 56319
B9: =SUMIF(E3:O31,"<0")*-1 -> 1688894 | C9: =SUMIF(J3:J31,"<0")*-1 -> 528923 | J9: -38760 | L9: -3270 | O9: 112640
J10: -21560 | L10: -9362 | O10: -2000
J11: -78190 | L11: -26052 | O11: -3295
J12: -78149 | L12: -2830 | O12: -3763
J13: -16663 | L13: -3780 | O13: -10000
J14: -9996 | L14: -4090
J15: -31333
J16: -10106
J17: =567894 -> 567894
J18: -12540
J19: -6390
J20: -10000
J21: 5044
J22: =-12160 -> -12160
J23: -10000
J24: -9027
J25: -15090
J26: -6000
J27: -53327
J28: -19147
J29: -10000
D34: Total c/u | E34: =SUM(E3:E31) -> 0 | F34: =SUM(F3:F31) -> 0 | G34: =SUM(G3:G31) -> 1041112 | H34: =SUM(H3:H31) -> 0 | I34: =SUM(I3:I31) -> 0 | J34: =SUM(J3:J31) -> 380066 | K34: =SUM(K3:K31) -> -62578 | L34: =SUM(L3:L31) -> -28253 | ... O34: =SUM(O3:O31) -> 1965708 | P34: =SUM(E34:O34) -> 4180327
